geochron/__init__.py
geochron/_version.py
geochron/chronnet.py
geochron/geosynchnet.py
geochron/geotimehash.py
geochron/py.typed
geochron/time_grid.py
geochron/time_slicing.py
geochron/timehex.py
geochron/utils/__init__.py
geochron/utils/conditional_imports.py
geochron/visualization/__init__.py
geochron/visualization/folium.py
geochron/visualization/pydeck.py
geochron-0.6.1.dist-info/LICENSE
geochron-0.6.1.dist-info/METADATA
geochron-0.6.1.dist-info/WHEEL
geochron-0.6.1.dist-info/top_level.txt
geochron-0.6.1.dist-info/RECORD
