Metadata-Version: 2.1
Name: geochron
Version: 0.6.1
Summary: A companion package to geostructures enabling geo-spatial-temporal data structures.
Home-page: https://github.com/etalbert102/geochron
Author: Eli Talbert
Author-email: 
Classifier: Programming Language :: Python :: 3
Classifier: Operating System :: OS Independent
Requires-Python: >=3.8
License-File: LICENSE
Requires-Dist: geostructures <1.0,>=0.10.0
Requires-Dist: numpy <2,>=1
Requires-Dist: pandas <3,>=2
